{
  "generated": "2026-02-08T22:25:09Z",
  "products": [
    {
      "name": "Contrast CLI Linux",
      "slug": "contrast-cli-linux",
      "source": "artifactory",
      "versions": [
      ]
    }
,
    {
      "name": "Contrast CLI Mac",
      "slug": "contrast-cli-mac",
      "source": "artifactory",
      "versions": [
      ]
    }
,
    {
      "name": "Contrast CLI Windows",
      "slug": "contrast-cli-windows",
      "source": "artifactory",
      "versions": [
      ]
    }
,
    {
      "name": "EOP",
      "slug": "eop",
      "source": "s3",
      "versions": [
        {
          "version": "3.12.10",
          "generatedAt": "2026-02-08T22:24:17Z",
          "formats": ["spdx","cyclonedx"]
        }
,
        {
          "version": "3.12.9",
          "generatedAt": "2026-02-08T22:24:17Z",
          "formats": ["spdx","cyclonedx"]
        }
,
        {
          "version": "3.12.8",
          "generatedAt": "2026-02-08T22:24:17Z",
          "formats": ["spdx","cyclonedx"]
        }
,
        {
          "version": "3.12.7",
          "generatedAt": "2026-02-08T22:24:17Z",
          "formats": ["spdx","cyclonedx"]
        }
,
        {
          "version": "3.12.6",
          "generatedAt": "2026-02-08T22:24:17Z",
          "formats": ["spdx","cyclonedx"]
        }
,
        {
          "version": "3.12.5",
          "generatedAt": "2026-02-08T22:24:17Z",
          "formats": ["spdx","cyclonedx"]
        }
,
        {
          "version": "3.12.4-PATCH",
          "generatedAt": "2026-02-08T22:24:17Z",
          "formats": ["spdx","cyclonedx"]
        }
,
        {
          "version": "3.12.4",
          "generatedAt": "2026-02-08T22:24:17Z",
          "formats": ["spdx","cyclonedx"]
        }
,
        {
          "version": "3.12.3",
          "generatedAt": "2026-02-08T22:24:17Z",
          "formats": ["spdx","cyclonedx"]
        }
,
        {
          "version": "3.12.2",
          "generatedAt": "2026-02-08T22:24:17Z",
          "formats": ["spdx","cyclonedx"]
        }
,
        {
          "version": "3.12.1",
          "generatedAt": "2026-02-08T22:24:17Z",
          "formats": ["spdx","cyclonedx"]
        }
,
        {
          "version": "3.12.0",
          "generatedAt": "2026-02-08T22:24:17Z",
          "formats": ["spdx","cyclonedx"]
        }
,
        {
          "version": "3.11.11",
          "generatedAt": "2026-02-08T22:24:17Z",
          "formats": ["spdx","cyclonedx"]
        }
      ]
    }
,
    {
      "name": "Flex Agent",
      "slug": "flex-agent",
      "source": "artifactory",
      "versions": [
      ]
    }
,
    {
      "name": "Go Agent (Linux AMD64)",
      "slug": "go-agent-linux-amd64",
      "source": "artifactory",
      "versions": [
      ]
    }
,
    {
      "name": "Java Agent",
      "slug": "java-agent",
      "source": "maven",
      "versions": [
        {
          "version": "6.25.1",
          "generatedAt": "2026-02-08T22:24:40Z",
          "formats": ["spdx","cyclonedx"]
        }
,
        {
          "version": "6.25.0",
          "generatedAt": "2026-02-08T22:24:43Z",
          "formats": ["spdx","cyclonedx"]
        }
,
        {
          "version": "6.24.0",
          "generatedAt": "2026-02-08T22:24:45Z",
          "formats": ["spdx","cyclonedx"]
        }
,
        {
          "version": "6.23.0",
          "generatedAt": "2026-02-08T22:24:48Z",
          "formats": ["spdx","cyclonedx"]
        }
,
        {
          "version": "6.22.1",
          "generatedAt": "2026-02-08T22:24:51Z",
          "formats": ["spdx","cyclonedx"]
        }
,
        {
          "version": "6.22.0",
          "generatedAt": "2026-02-08T22:24:53Z",
          "formats": ["spdx","cyclonedx"]
        }
,
        {
          "version": "6.21.0",
          "generatedAt": "2026-02-08T22:24:56Z",
          "formats": ["spdx","cyclonedx"]
        }
,
        {
          "version": "6.20.1",
          "generatedAt": "2026-02-08T22:24:58Z",
          "formats": ["spdx","cyclonedx"]
        }
,
        {
          "version": "6.19.0",
          "generatedAt": "2026-02-08T22:25:01Z",
          "formats": ["spdx","cyclonedx"]
        }
,
        {
          "version": "6.18.1",
          "generatedAt": "2026-02-08T22:25:04Z",
          "formats": ["spdx","cyclonedx"]
        }
      ]
    }
,
    {
      "name": "Node Agent",
      "slug": "node-agent",
      "source": "artifactory",
      "versions": [
      ]
    }
,
    {
      "name": "Python Agent",
      "slug": "python-agent",
      "source": "artifactory",
      "versions": [
      ]
    }
,
    {
      "name": "Ruby Agent",
      "slug": "ruby-agent",
      "source": "artifactory",
      "versions": [
      ]
    }
  ]
}
